telega_notify/__init__.py
telega_notify/main.py
telega_notify-0.1.dist-info/DESCRIPTION.rst
telega_notify-0.1.dist-info/METADATA
telega_notify-0.1.dist-info/RECORD
telega_notify-0.1.dist-info/WHEEL
telega_notify-0.1.dist-info/entry_points.txt
telega_notify-0.1.dist-info/metadata.json
telega_notify-0.1.dist-info/top_level.txt
